datesearch/__init__.py
datesearch/search.py
datesearch/tokenizator.py
datesearch/tokens/__init__.py
datesearch/tokens/abstract_token.py
datesearch/tokens/dilimiter.py
datesearch/tokens/number.py
datesearch/tokens/other.py
datesearch/tokens/period.py
datesearch/tokens/punctuation.py
datesearch-0.0.1.dist-info/METADATA
datesearch-0.0.1.dist-info/WHEEL
datesearch-0.0.1.dist-info/top_level.txt
datesearch-0.0.1.dist-info/RECORD
