Metadata-Version: 2.1
Name: datesearch
Version: 0.0.1
Summary: Поиск токенов, относящихся к датам, по регулярным выражениям
Home-page: https://github.com/pomponchik/datesearch
Author: Evgeniy Blinov
Author-email: zheni-b@yandex.ru
License: UNKNOWN
Platform: UNKNOWN
Classifier: Programming Language :: Python :: 3.8
Classifier: License :: OSI Approved :: MIT License
Requires-Dist: pymorphy2 (==0.8)
Requires-Dist: pymorphy2-dicts-ru (==2.4.404381.4453942)
